allison/__init__.py
allison/clustering/__init__.py
allison/clustering/k_means.py
allison/cuda/__init__.py
allison/cuda/cuda.py
allison/cupy/cupy.py
allison/datasets/__init__.py
allison/datasets/dataloader.py
allison/datasets/dataset.py
allison/datasets/train_test.py
allison/metrics/__init__.py
allison/metrics/metrics.py
allison/nn/__init__.py
allison/nn/layers.py
allison/nn/loss.py
allison/nn/net.py
allison/optim/__init__.py
allison/optim/optim.py
allison/preprocessing/__init__.py
allison/preprocessing/enconders.py
allison/preprocessing/scalers.py
allison/preprocessing/transformers.py
allison/tensor/tensor.py
allison/utils/math.py
allison/utils/utils.py
allison-1.3.0.dist-info/licenses/LICENSE
allison-1.3.0.dist-info/METADATA
allison-1.3.0.dist-info/WHEEL
allison-1.3.0.dist-info/top_level.txt
allison-1.3.0.dist-info/RECORD
