Metadata-Version: 2.4
Name: allison
Version: 1.3.0
Summary: ⚠️ Deprecated: Allison has been renamed to Sorix. Please install 'sorix' instead.
Author-email: Mitchell Mirano <mitchellmirano25@gmail.com>
License: MIT
Project-URL: Migration Notice, https://pypi.org/project/sorix/
Project-URL: New Package (Sorix), https://pypi.org/project/sorix/
Project-URL: GitHub (Allison - Archived), https://github.com/Mitchell-Mirano/Allison
Project-URL: GitHub (Sorix - Active), https://github.com/Mitchell-Mirano/sorix
Project-URL: Author, https://github.com/Mitchell-Mirano
Requires-Python: >=3.12
License-File: LICENSE
Requires-Dist: numpy<3.0,>=2.0
Provides-Extra: cp13
Requires-Dist: cupy-cuda13x>=13.0; extra == "cp13"
Requires-Dist: numpy<3.0,>=2.0; extra == "cp13"
Dynamic: license-file
